extraire/__init__.py
extraire/__main__.py
extraire/extraire.py
extraire/pyimg4.py
extraire-0.1.4.post1.dist-info/entry_points.txt
extraire-0.1.4.post1.dist-info/LICENSE
extraire-0.1.4.post1.dist-info/WHEEL
extraire-0.1.4.post1.dist-info/METADATA
extraire-0.1.4.post1.dist-info/RECORD
