Metadata-Version: 2.1
Name: extraire
Version: 0.1.4.post1
Summary: Dumps onboard SHSH blobs with a valid generator for jailbroken iOS devices
License: 0BSD
Keywords: ios,jailbreak,iboot,img4,shsh,blob
Author: beerpiss
Author-email: lacvtg.a1.2023@gmail.com
Requires-Python: >=3.6.2,<3.11
Classifier: Development Status :: 4 - Beta
Classifier: Environment :: Console
Classifier: License :: Other/Proprietary License
Classifier: Programming Language :: Python :: 3
Classifier: Programming Language :: Python :: 3 :: Only
Classifier: Programming Language :: Python :: 3.10
Classifier: Programming Language :: Python :: 3.6
Classifier: Programming Language :: Python :: 3.7
Classifier: Programming Language :: Python :: 3.8
Classifier: Programming Language :: Python :: 3.9
Classifier: Topic :: Utilities
Requires-Dist: fabric (>=2.7.0,<3.0.0)
Requires-Dist: pyasn1 (>=0.4.8,<0.5.0)
Requires-Dist: rich (>=12.0.1,<13.0.0)
Project-URL: Bug Tracker, https://github.com/beerpiss/extraire/issues
